ReplaceMarkersInDocxAJM/ReplaceMarkersInDocxAJM.py
ReplaceMarkersInDocxAJM/ReplaceMarkersInDocxAJM.pyi
ReplaceMarkersInDocxAJM/__init__.py
ReplaceMarkersInDocxAJM/_version.py
replacemarkersindocxajm-0.2.dist-info/licenses/LICENSE.txt
replacemarkersindocxajm-0.2.dist-info/METADATA
replacemarkersindocxajm-0.2.dist-info/WHEEL
replacemarkersindocxajm-0.2.dist-info/top_level.txt
replacemarkersindocxajm-0.2.dist-info/RECORD
