Metadata-Version: 2.4
Name: ReplaceMarkersInDocxAJM
Version: 0.2
Summary: *** Overall project description goes here ***
Home-page: https://github.com/amcsparron2793-Water/ReplaceMarkersInDocxAJM
Download-URL: https://github.com/amcsparron2793-Water/ReplaceMarkersInDocxAJM/archive/refs/tags/0.2.tar.gz
Author: Amcsparron
Author-email: amcsparron@albanyny.gov
License: MIT License
Classifier: Development Status :: 3 - Alpha
Classifier: Intended Audience :: Developers
Classifier: Topic :: Software Development :: Build Tools
Classifier: License :: OSI Approved :: MIT License
Classifier: Programming Language :: Python :: 3
License-File: LICENSE.txt
Dynamic: author
Dynamic: author-email
Dynamic: classifier
Dynamic: description
Dynamic: description-content-type
Dynamic: download-url
Dynamic: home-page
Dynamic: license
Dynamic: license-file
Dynamic: summary
